{
    "paraphrases": [],
    "sentence": "cheapest fare from , indianapolis to orlando on the , twenty seventh of december",
    "sq2": "SELECT DISTINCT  v0.one_direction_cost, '\"'||v13.fare_basis_code||'\"',\n '\"'||v14.days_code||'\"', '\"'||v15.day_name||'\"', v15.year,\n v15.month_number, v15.day_number, '\"'||v16.fare_id||'\"',\n '\"'||v17.flight_id||'\"', '\"'||v18.airport_code||'\"', '\"'||v19.city_code||'\"',\n '\"'||v19.city_name||'\"', '\"'||v20.airport_code||'\"',\n '\"'||v21.city_code||'\"', '\"'||v21.city_name||'\"',\n '\"'||v22.days_code||'\"', '\"'||v23.day_name||'\"', v23.year,\n v23.month_number, v23.day_number FROM fare v0, fare_basis v13,\n days v14, date_day v15, flight_fare v16, flight v17,\n airport_service v18, city v19, airport_service v20, city v21,\n days v22, date_day v23 \nWHERE ((v0.one_direction_cost = (\nSELECT MIN (v1.one_direction_cost) FROM fare v1 \nWHERE ((v1.fare_basis_code IN (\nSELECT v2.fare_basis_code FROM fare_basis v2 \nWHERE (v2.basis_days IN (\nSELECT v3.days_code FROM days v3 \nWHERE (v3.day_name IN (\nSELECT v4.day_name FROM date_day v4 \nWHERE (((v4.year =  1993) AND (v4.month_number =  12)) AND (v4.day_number =  27)))))))) \nAND (v1.fare_id IN (\nSELECT v5.fare_id FROM flight_fare v5 \nWHERE (v5.flight_id IN (\nSELECT v6.flight_id FROM flight v6 \nWHERE ((v6.from_airport IN (\nSELECT v7.airport_code FROM airport_service v7 \nWHERE (v7.city_code IN (\nSELECT v8.city_code FROM city v8 \nWHERE (v8.city_name = 'INDIANAPOLIS'))))) \nAND ((v6.to_airport IN (\nSELECT v9.airport_code FROM airport_service v9 \nWHERE (v9.city_code IN (\nSELECT v10.city_code FROM city v10 \nWHERE (v10.city_name = 'ORLANDO'))))) \nAND (v6.flight_days IN (\nSELECT v11.days_code FROM days v11 \nWHERE (v11.day_name IN (\nSELECT v12.day_name FROM date_day v12 \nWHERE (((v12.year =  1993) AND (v12.month_number =  12)) \nAND (v12.day_number =  27))))))))))))))) AND (((v0.fare_basis_code = ANY v13.fare_basis_code) \nAND ((v13.basis_days = ANY v14.days_code) \nAND ((v14.day_name = ANY v15.day_name) \nAND (((v15.year =  1993) AND (v15.month_number =  12)) AND (v15.day_number =  27))))) \nAND ((v0.fare_id = ANY v16.fare_id) \nAND ((v16.flight_id = ANY v17.flight_id) AND (((v17.from_airport = ANY v18.airport_code) \nAND ((v18.city_code = ANY v19.city_code) \nAND (v19.city_name = 'INDIANAPOLIS'))) AND (((v17.to_airport = ANY v20.airport_code) \nAND ((v20.city_code = ANY v21.city_code) \nAND (v21.city_name = 'ORLANDO'))) AND ((v17.flight_days = ANY v22.days_code) \nAND ((v22.day_name = ANY v23.day_name) \nAND (((v23.year =  1993) AND (v23.month_number =  12)) \nAND (v23.day_number =  27))))))))));",
    "sql": [
        "( SELECT DISTINCT FARE.FARE_ID FROM FARE WHERE ( FARE.ONE_DIRECTION_COST = ( SELECT MIN ( FARE.ONE_DIRECTION_COST ) FROM FARE WHERE ( FARE . FARE_BASIS_CODE IN ( SELECT FARE_BASIS . FARE_BASIS_CODE FROM FARE_BASIS WHERE FARE_BASIS . BASIS_DAYS IN ( SELECT DAYS . DAYS_CODE FROM DAYS WHERE DAYS.DAY_NAME IN ( SELECT DATE_DAY.DAY_NAME FROM DATE_DAY WHERE DATE_DAY.YEAR = 1993 AND DATE_DAY.MONTH_NUMBER = 12 AND DATE_DAY.DAY_NUMBER = 27 ) ) ) AND FARE . FARE_ID IN ( SELECT FLIGHT_FARE . FARE_ID FROM FLIGHT_FARE WHERE FLIGHT_FARE . FLIGHT_ID IN ( SELECT FLIGHT . FLIGHT_ID FROM FLIGHT WHERE ( FLIGHT . FROM_AIRPORT IN ( SELECT AIRPORT_SERVICE . AIRPORT_CODE FROM AIRPORT_SERVICE WHERE AIRPORT_SERVICE . CITY_CODE IN ( SELECT CITY . CITY_CODE FROM CITY WHERE CITY.CITY_NAME = ' INDIANAPOLIS ' ) ) AND ( FLIGHT . TO_AIRPORT IN ( SELECT AIRPORT_SERVICE . AIRPORT_CODE FROM AIRPORT_SERVICE WHERE AIRPORT_SERVICE . CITY_CODE IN ( SELECT CITY . CITY_CODE FROM CITY WHERE CITY.CITY_NAME = ' ORLANDO ' ) ) AND FLIGHT . FLIGHT_DAYS IN ( SELECT DAYS . DAYS_CODE FROM DAYS WHERE DAYS.DAY_NAME IN ( SELECT DATE_DAY.DAY_NAME FROM DATE_DAY WHERE DATE_DAY.YEAR = 1993 AND DATE_DAY.MONTH_NUMBER = 12 AND DATE_DAY.DAY_NUMBER = 27 ) ) ) ) ) ) ) ) AND ( FARE . FARE_BASIS_CODE IN ( SELECT FARE_BASIS . FARE_BASIS_CODE FROM FARE_BASIS WHERE FARE_BASIS . BASIS_DAYS IN ( SELECT DAYS . DAYS_CODE FROM DAYS WHERE DAYS.DAY_NAME IN ( SELECT DATE_DAY.DAY_NAME FROM DATE_DAY WHERE DATE_DAY.YEAR = 1993 AND DATE_DAY.MONTH_NUMBER = 12 AND DATE_DAY.DAY_NUMBER = 27 ) ) ) AND FARE . FARE_ID IN ( SELECT FLIGHT_FARE . FARE_ID FROM FLIGHT_FARE WHERE FLIGHT_FARE . FLIGHT_ID IN ( SELECT FLIGHT . FLIGHT_ID FROM FLIGHT WHERE ( FLIGHT . FROM_AIRPORT IN ( SELECT AIRPORT_SERVICE . AIRPORT_CODE FROM AIRPORT_SERVICE WHERE AIRPORT_SERVICE . CITY_CODE IN ( SELECT CITY . CITY_CODE FROM CITY WHERE CITY.CITY_NAME = ' INDIANAPOLIS ' ) ) AND ( FLIGHT . TO_AIRPORT IN ( SELECT AIRPORT_SERVICE . AIRPORT_CODE FROM AIRPORT_SERVICE WHERE AIRPORT_SERVICE . CITY_CODE IN ( SELECT CITY . CITY_CODE FROM CITY WHERE CITY.CITY_NAME = ' ORLANDO ' ) ) AND FLIGHT . FLIGHT_DAYS IN ( SELECT DAYS . DAYS_CODE FROM DAYS WHERE DAYS.DAY_NAME IN ( SELECT DATE_DAY.DAY_NAME FROM DATE_DAY WHERE DATE_DAY.YEAR = 1993 AND DATE_DAY.MONTH_NUMBER = 12 AND DATE_DAY.DAY_NUMBER = 27 ) ) ) ) ) ) ) ) ) ;"
    ],
    "variables": []
}
