{
    "accuracy": [
        "JKK - 1",
        "LZ - 1"
    ],
    "comments": [
        "JKK - Student specific case"
    ],
    "helpfulness": [
        "JKK - 2",
        "LZ - 2"
    ],
    "info": [],
    "paraphrases": [
        "After taking what courses can I take 489 ?",
        "Any prerequisits for course 489 ?",
        "Are there any classes I need to take before 489 , and if so , which ones ?",
        "Are there any courses I must have previously taken to enroll in 489 ?",
        "Are there any courses I must take before taking 489 ?",
        "Are there any courses required prior to taking 489 ?",
        "Are there any courses that I am required to take before course 489 ?",
        "Are there any courses that I 'm required to take before taking 489 ?",
        "Are there any prerequisites courses to take before EECS 489 ?",
        "Are there classes I have to take before EECS 489 ?",
        "Are there classes I need to take before EECS 489 ?",
        "Are there courses I have to take before EECS 489 ?",
        "Are there courses I must take before EECS 489 ?",
        "Are there courses I need to take before 489 ?",
        "Are there courses I need to take before EECS 489 ?",
        "Are there courses I need to take before taking 489 ?",
        "Are there courses prior to EECS 489 I should be taking ?",
        "Are there courses prior to EECS 489 that I have to do ?",
        "Before 489 what courses do I need ?",
        "Before 489 , which courses do I need to take ?",
        "Before I take 489 what do I need to take ?",
        "Before I take 489 , what other courses do I need to complete ?",
        "Before I take 489 , which other courses must I complete ?",
        "Before taking 489 , what classes must I complete ?",
        "Before taking 489 , what courses must I take ?",
        "Before taking 489 , which courses do I need to take ?",
        "Before taking 489 , which courses do I need ?",
        "Before taking 489 , which courses do i need to take ?",
        "Before taking EECS 489 do I need to take any courses ?",
        "Before taking course 489 , which courses do I need to take ?",
        "Before taking course 489 , which courses need I take ?",
        "Do I need to take any classes before taking EECS 489 ?",
        "Do I need to take any courses before 489 ?",
        "Do I need to take any courses before taking 489 ?",
        "Do I need to take any specific courses before taking 489 ?",
        "Do I need to take courses before taking 489 ?",
        "Does EECS 489 have any prerequisites ?",
        "EECS 489 requires me to take what classes before I can take it ?",
        "For EECS 489 what are the classes needed to be taken ?",
        "In order to take 489 , what courses are required to be completed ?",
        "Is there a pre-requisite class before I can do 489 ?",
        "Name the classes that i need to take before taking EECS 489 .",
        "Name the classes that need to be taken before EECS 489 .",
        "Name the courses that i need to take before EECS 489 .",
        "Of all the courses , which ones have to be taken before taking 489 ?",
        "Prior to taking 489 what courses do I need to take ?",
        "Prior to taking 489 which courses should I take ?",
        "Prior to taking 489 , which courses do I need to complete ?",
        "To study EECS 489 which classes do i need to take ?",
        "What are the prerequisite courses to 489 ?",
        "What are the courses required before taking 489 ?",
        "What are the courses that I should take before 489 ?",
        "What are the pre requisite courses for 489",
        "What are the pre requisites for 489 ?",
        "What are the pre-requisites for 489 ?",
        "What are the prerequisite classes for 489 ?",
        "What are the prerequisite courses for 489 ?",
        "What are the prerequisite courses for EECS 489 ?",
        "What are the prerequisites for 489 ?",
        "What are the prerequisites for EECS 489 ?",
        "What are the prerequisites for me before enrolling in 489 ?",
        "What are the prerequisites for taking 489 ?",
        "What are the prerequisites to 489 ?",
        "What are the prerequites courses I need before taking 489 ?",
        "What are the required classes I need before taking 489 ?",
        "What are the required completed courses in order to take 489 ?",
        "What classes are a prerequisite for EECS 489 ?",
        "What classes are essential before I can start 489 ?",
        "What classes before 489 do I need to take ?",
        "What classes do I have to take before I can take EECS 489 ?",
        "What course requirements does 489 have ?",
        "What courses I am required to take before EECS 489 ?",
        "What courses are needed before I take 489 ?",
        "What courses are required as a prerequisite to 489 ?",
        "What courses are required before 489 ?",
        "What courses are required before taking EECS 489 ?",
        "What courses are required in order to take 489 ?",
        "What courses are the prerequisites needed for 489 ?",
        "What courses are the prerequisites to 489 ?",
        "What courses do I have to take before I can take EECS 489 ?",
        "What courses do I need to take before course 489 ?",
        "What courses do I need to take before taking 489 ?",
        "What courses must I take before 489 ?",
        "What courses must I take to be allowed to take 489 ?",
        "What courses must be completed to take 489 ?",
        "What is the prerequisite for 489 ?",
        "What other classes must I take prior to studying 489 ?",
        "What prerequisite courses fall before EECS 489",
        "Which course is required prior to the 489 course ?",
        "Which courses am I required to take prior to 489 ?",
        "Which courses are pre-requisite to taking 489 ?",
        "Which courses are required before I can take 489 ?",
        "Which courses are required before going into 489 ?",
        "Which courses are required before taking 489 ?",
        "Which courses are the prerequisites for 489 ?",
        "Which courses do I need before taking 489",
        "Which courses do I need to take before 489 ?",
        "Which courses do I need to take before taking 489 ?",
        "Which courses must be completed to be able to take 489 ?",
        "Which courses need to be taken before taking 489 ?"
    ],
    "sentence": "What prerequisites do I still need to take in order to take EECS 489 ?",
    "sentence-with-vars": "What prerequisites do I still need to take in order to take department0 number0 ?",
    "sql": [
        "SELECT DISTINCT COURSEalias0.NAME , COURSEalias0.NUMBER FROM COURSE AS COURSEalias0 , COURSE AS COURSEalias1 , COURSE_PREREQUISITE AS COURSE_PREREQUISITEalias0 WHERE COURSEalias0.COURSE_ID = COURSE_PREREQUISITEalias0.PRE_COURSE_ID AND COURSEalias0.COURSE_ID NOT IN ( SELECT STUDENT_RECORDalias0.COURSE_ID FROM STUDENT_RECORD AS STUDENT_RECORDalias0 WHERE STUDENT_RECORDalias0.STUDENT_ID = 1 ) AND COURSEalias1.COURSE_ID = COURSE_PREREQUISITEalias0.COURSE_ID AND COURSEalias1.DEPARTMENT = \"EECS\" AND COURSEalias1.NUMBER = 489 ;"
    ],
    "sql-with-vars": "SELECT DISTINCT COURSEalias0.NAME , COURSEalias0.NUMBER FROM COURSE AS COURSEalias0 , COURSE AS COURSEalias1 , COURSE_PREREQUISITE AS COURSE_PREREQUISITEalias0 WHERE COURSEalias0.COURSE_ID = COURSE_PREREQUISITEalias0.PRE_COURSE_ID AND COURSEalias0.COURSE_ID NOT IN ( SELECT STUDENT_RECORDalias0.COURSE_ID FROM STUDENT_RECORD AS STUDENT_RECORDalias0 WHERE STUDENT_RECORDalias0.STUDENT_ID = 1 ) AND COURSEalias1.COURSE_ID = COURSE_PREREQUISITEalias0.COURSE_ID AND COURSEalias1.DEPARTMENT = \"department0\" AND COURSEalias1.NUMBER = number0 ;",
    "unchecked-paraphrases": [],
    "variables": [
        {
            "name": "number0",
            "sentence-value": "489",
            "sql-value": "489"
        },
        {
            "name": "department0",
            "sentence-value": "EECS",
            "sql-value": "EECS"
        }
    ]
}